craps_pkg/__init__.py
craps_pkg/craps_pkg.py
craps_dice_combos_names-0.1.127.2.dist-info/METADATA
craps_dice_combos_names-0.1.127.2.dist-info/WHEEL
craps_dice_combos_names-0.1.127.2.dist-info/top_level.txt
craps_dice_combos_names-0.1.127.2.dist-info/RECORD
