Metadata-Version: 2.1
Name: craps-dice-combos-names
Version: 0.1.127.2
Summary: A miniscule library for generating and identifying dice combos in craps
Home-page: https://github.com/sharnajh/craps_pkg.git
Author: Sharna Hossain
Author-email: sharnajh@gmail.com
License: BSD 2-clause
Platform: UNKNOWN
Classifier: License :: OSI Approved :: MIT License
Classifier: Operating System :: MacOS
Classifier: Programming Language :: Python :: 2
Classifier: Programming Language :: Python :: 2.7
Classifier: Programming Language :: Python :: 3
Classifier: Programming Language :: Python :: 3.4
Classifier: Programming Language :: Python :: 3.5
Classifier: Topic :: Games/Entertainment
Classifier: Topic :: Games/Entertainment :: Turn Based Strategy
Classifier: Topic :: Games/Entertainment :: Simulation
Classifier: Topic :: Games/Entertainment :: Arcade
